ltldoorstep/__init__.py
ltldoorstep/artifact.py
ltldoorstep/aspect.py
ltldoorstep/config.py
ltldoorstep/context.py
ltldoorstep/crawler.py
ltldoorstep/data_store.py
ltldoorstep/document_utils.py
ltldoorstep/encoders.py
ltldoorstep/errors.py
ltldoorstep/file.py
ltldoorstep/flask_server.py
ltldoorstep/ini.py
ltldoorstep/location_utils.py
ltldoorstep/printer.py
ltldoorstep/processor.py
ltldoorstep/regex_utils.py
ltldoorstep/wamp_client.py
ltldoorstep/wamp_server.py
ltldoorstep/watch.py
ltldoorstep/engines/__init__.py
ltldoorstep/engines/dask_common.py
ltldoorstep/engines/dask_distributed.py
ltldoorstep/engines/dask_threaded.py
ltldoorstep/engines/docker.py
ltldoorstep/engines/engine.py
ltldoorstep/engines/openfaas.py
ltldoorstep/engines/sandbox.py
ltldoorstep/reports/__init__.py
ltldoorstep/reports/collection.py
ltldoorstep/reports/document.py
ltldoorstep/reports/geojson.py
ltldoorstep/reports/report.py
ltldoorstep/reports/tabular.py
ltldoorstep/scripts/__init__.py
ltldoorstep/scripts/ltldoorstep.py
ltldoorstep/scripts/ltlwampclient.py
ltldoorstep/templates/head.html
ltldoorstep/templates/tail.html
ltldoorstep-0.3.4.dist-info/LICENSE
ltldoorstep-0.3.4.dist-info/LICENSE.md
ltldoorstep-0.3.4.dist-info/METADATA
ltldoorstep-0.3.4.dist-info/WHEEL
ltldoorstep-0.3.4.dist-info/entry_points.txt
ltldoorstep-0.3.4.dist-info/top_level.txt
ltldoorstep-0.3.4.dist-info/RECORD
