Metadata-Version: 2.1
Name: ltldoorstep
Version: 0.3.4
Summary: Doorstep: Project Lintol validation engine
Home-page: https://github.com/lintol/doorstep
Author: Project Lintol team (on behalf of)
Author-email: help@lintol.io
License: MIT
Keywords: validation lintol data
Platform: UNKNOWN
Classifier: Development Status :: 3 - Alpha
Classifier: Intended Audience :: Developers
Classifier: License :: OSI Approved :: MIT License
Classifier: Programming Language :: Python :: 3.5
Requires-Dist: Click (>=7.0)
Requires-Dist: janus
Requires-Dist: colorama
Requires-Dist: dask
Requires-Dist: distributed
Requires-Dist: chardet (<4.0)
Requires-Dist: unidecode
Requires-Dist: tabulate
Requires-Dist: flask (>1.0)
Requires-Dist: flask-restful
Requires-Dist: pandas
Requires-Dist: boto3
Requires-Dist: autobahn
Requires-Dist: ckanapi
Requires-Dist: requests
Requires-Dist: docker
Requires-Dist: retry
Requires-Dist: minio
Requires-Dist: aiohttp
Requires-Dist: aiodocker
Provides-Extra: babel-commands
Requires-Dist: Babel ; extra == 'babel-commands'
Provides-Extra: examples
Requires-Dist: shapely ; extra == 'examples'
Requires-Dist: piianalyzer ; extra == 'examples'
Requires-Dist: geojson-utils ; extra == 'examples'
Requires-Dist: geopandas ; extra == 'examples'
Provides-Extra: sphinx-commands
Requires-Dist: sphinx ; extra == 'sphinx-commands'
